[
  [
    "web3h3nry",
    {
      "posts": 7,
      "likes": 723,
      "retweets": 186,
      "comments": 177,
      "quotes": 36,
      "views": 15656
    }
  ],
  [
    "imose_eth",
    {
      "posts": 2,
      "likes": 53,
      "retweets": 4,
      "comments": 12,
      "quotes": 0,
      "views": 3573
    }
  ],
  [
    "nandaxthe",
    {
      "posts": 2,
      "likes": 19,
      "retweets": 4,
      "comments": 2,
      "quotes": 2,
      "views": 568
    }
  ],
  [
    "Dangos_eth",
    {
      "posts": 11,
      "likes": 96,
      "retweets": 9,
      "comments": 33,
      "quotes": 9,
      "views": 2462
    }
  ],
  [
    "SzMakhachev",
    {
      "posts": 2,
      "likes": 5,
      "retweets": 1,
      "comments": 1,
      "quotes": 0,
      "views": 116
    }
  ],
  [
    "ThatReply_Guy",
    {
      "posts": 1,
      "likes": 2,
      "retweets": 1,
      "comments": 0,
      "quotes": 0,
      "views": 45
    }
  ],
  [
    "TheCryptoAlchim",
    {
      "posts": 2,
      "likes": 11,
      "retweets": 0,
      "comments": 1,
      "quotes": 0,
      "views": 147
    }
  ],
  [
    "Web3Phant0m",
    {
      "posts": 1,
      "likes": 1,
      "retweets": 0,
      "comments": 0,
      "quotes": 0,
      "views": 49
    }
  ],
  [
    "mirza_sarmin",
    {
      "posts": 2,
      "likes": 3,
      "retweets": 0,
      "comments": 0,
      "quotes": 0,
      "views": 43
    }
  ],
  [
    "F8T_eth",
    {
      "posts": 4,
      "likes": 23,
      "retweets": 3,
      "comments": 0,
      "quotes": 3,
      "views": 815
    }
  ],
  [
    "Thiennam789",
    {
      "posts": 2,
      "likes": 26,
      "retweets": 0,
      "comments": 11,
      "quotes": 0,
      "views": 507
    }
  ],
  [
    "0x_vagrant",
    {
      "posts": 3,
      "likes": 32,
      "retweets": 0,
      "comments": 11,
      "quotes": 0,
      "views": 450
    }
  ],
  [
    "pedrotatana1",
    {
      "posts": 2,
      "likes": 5,
      "retweets": 0,
      "comments": 0,
      "quotes": 0,
      "views": 72
    }
  ],
  [
    "Ruslan_nero",
    {
      "posts": 2,
      "likes": 16,
      "retweets": 4,
      "comments": 6,
      "quotes": 2,
      "views": 305
    }
  ],
  [
    "9th_unknown",
    {
      "posts": 2,
      "likes": 13,
      "retweets": 0,
      "comments": 0,
      "quotes": 0,
      "views": 332
    }
  ],
  [
    "kaye_moni",
    {
      "posts": 1,
      "likes": 80,
      "retweets": 3,
      "comments": 18,
      "quotes": 0,
      "views": 674
    }
  ],
  [
    "ShazamWeb3",
    {
      "posts": 3,
      "likes": 19,
      "retweets": 0,
      "comments": 3,
      "quotes": 0,
      "views": 307
    }
  ],
  [
    "kiavashrasta",
    {
      "posts": 1,
      "likes": 4,
      "retweets": 0,
      "comments": 3,
      "quotes": 0,
      "views": 74
    }
  ],
  [
    "preshly90",
    {
      "posts": 1,
      "likes": 8,
      "retweets": 1,
      "comments": 1,
      "quotes": 0,
      "views": 165
    }
  ]
]